MeshCom_Client/__init__.py
MeshCom_Client/__main__.py
MeshCom_Client/settingsdialog.py
MeshCom_Client/watchlistdialog.py
MeshCom_Client/locales/MeshCom-Client.pot
MeshCom_Client/locales/de/LC_MESSAGES/MeshCom-Client.mo
MeshCom_Client/locales/de/LC_MESSAGES/MeshCom-Client.po
MeshCom_Client/locales/en/LC_MESSAGES/MeshCom-Client.mo
MeshCom_Client/locales/en/LC_MESSAGES/MeshCom-Client.po
MeshCom_Client/sounds/alert.wav
MeshCom_Client/sounds/mycall.wav
MeshCom_Client/sounds/new_message.wav
meshcom_client-1.0.13.dist-info/licenses/LICENSE
meshcom_client-1.0.13.dist-info/METADATA
meshcom_client-1.0.13.dist-info/WHEEL
meshcom_client-1.0.13.dist-info/entry_points.txt
meshcom_client-1.0.13.dist-info/top_level.txt
meshcom_client-1.0.13.dist-info/RECORD
