Metadata-Version: 2.4
Name: MeshCom-Client
Version: 1.0.13
Summary: Python MeshCom-Client for udp communication with MeshCom nodes
License-File: LICENSE
Requires-Dist: pygame>=2.1.2
Dynamic: license-file
